{
  "generated_at": "2026-05-21T05:58:35.502785",
  "top_stories": [
    {
      "title": "Grief Doc ‘The Last Note’ Acquired by HG Distribution as Fusee Launches Three-Doc Slate at Cannes Film Market (EXCLUSIVE)",
      "source": "Variety",
      "date": "2026-05-21",
      "url": "https://variety.com/2026/film/markets-festivals/fusee-documentary-slate-cannes-the-last-note-1236755690/"
    },
    {
      "title": "Bruce Springsteen Calls Out Trump, Larry and David Ellison in Colbert’s Second-to-Last ‘Late Show’",
      "source": "Variety",
      "date": "2026-05-21",
      "url": "https://variety.com/2026/tv/news/bruce-springsteen-stephen-colbert-late-show-trump-larry-david-ellison-1236755680/"
    },
    {
      "title": "‘The Late Show’: Stephen Colbert Brings Out Robert De Niro, Martha Stewart and Tons of Others to Quiz Him in Second-to-Last Episode",
      "source": "Variety",
      "date": "2026-05-21",
      "url": "https://variety.com/2026/tv/news/the-late-show-stephen-colbert-robert-de-niro-martha-stewart-1236755672/"
    }
  ],
  "new_releases": [
    {
      "title": "驚きから不安、そして“恐怖”へと深化…鎮西寿々歌主演ホラー「だぁれかさんとアソぼ？」場面写真公開",
      "source": "映画.com",
      "date": "2026-05-20",
      "url": "https://eiga.com/news/20260521/6/"
    },
    {
      "title": "鬼才レフン監督、DC映画「バットガール」に志願",
      "source": "映画.com",
      "date": "2026-05-21",
      "url": "https://eiga.com/news/20260521/15/"
    },
    {
      "title": "チ・チャンウク×今田美桜主演の日韓合作ラブコメ「メリーベリーラブ」 にナム・ユンス参戦",
      "source": "映画.com",
      "date": "2026-05-21",
      "url": "https://eiga.com/news/20260521/14/"
    },
    {
      "title": "ガールズフィッシング漫画「つりこまち」実写映画化決定！ ビジュアル＆原作者メッセージ公開",
      "source": "映画.com",
      "date": "2026-05-21",
      "url": "https://eiga.com/news/20260521/12/"
    },
    {
      "title": "目黒蓮主演「SAKAMOTO DAYS」坂本家の“家族愛”が詰まった心温まる新場面写真＆オフショット公開",
      "source": "映画.com",
      "date": "2026-05-21",
      "url": "https://eiga.com/news/20260521/11/"
    },
    {
      "title": "稲垣吾郎×草彅剛×香取慎吾「バナ穴 BANA_ANA」公開日は6月27日に決定！予測不能な新ビジュアル披露",
      "source": "映画.com",
      "date": "2026-05-21",
      "url": "https://eiga.com/news/20260521/13/"
    },
    {
      "title": "韓国中を沸かせたラブストーリー「サヨナラの引⼒」新場面写真とク・ギョファン＆ムン・ガヨンのメッセージ入り動画公開",
      "source": "映画.com",
      "date": "2026-05-21",
      "url": "https://eiga.com/news/20260521/10/"
    },
    {
      "title": "伊藤万理華、松本まりか×高橋メアリージュン主演「エミリとマリア」参戦　2人と世代ギャップを感じるネイリスト役",
      "source": "映画.com",
      "date": "2026-05-21",
      "url": "https://eiga.com/news/20260521/9/"
    },
    {
      "title": "1986年メキシコW杯誘致に隠された嘘とハッタリ「メヒコ 1986」6月5日からNetflixで配信",
      "source": "映画.com",
      "date": "2026-05-21",
      "url": "https://eiga.com/news/20260521/8/"
    },
    {
      "title": "4Kデジタルリマスター版「魔女の宅急便」IMAX予告映像公開 入場者プレゼントも限定配布",
      "source": "映画.com",
      "date": "2026-05-20",
      "url": "https://eiga.com/news/20260521/3/"
    },
    {
      "title": "藤原竜也×広瀬アリス「全領域異常解決室」劇場版、2部作に！　2027年春公開へ変更",
      "source": "映画.com",
      "date": "2026-05-20",
      "url": "https://eiga.com/news/20260521/7/"
    },
    {
      "title": "吉田羊、沖田修一監督「さとこはいつも」に国語教師役で出演",
      "source": "映画.com",
      "date": "2026-05-20",
      "url": "https://eiga.com/news/20260521/5/"
    },
    {
      "title": "二宮和也がアンバサダーに就任！　幕が開くまでタイトルは“秘密”　「シークレットシネマ」6月25日開催決定！",
      "source": "映画.com",
      "date": "2026-05-20",
      "url": "https://eiga.com/news/20260521/4/"
    },
    {
      "title": "黒木メイサ主演「八神瑛子」の警察キャストに高良健吾、池内博之、内村颯太の出演が決定！ コメントも公開",
      "source": "映画.com",
      "date": "2026-05-20",
      "url": "https://eiga.com/news/20260521/2/"
    },
    {
      "title": "「劇場版TOKYO MER」第3弾に【南海MER】江口洋介、高杉真宙、生見愛瑠、宮澤エマの出演が決定！",
      "source": "映画.com",
      "date": "2026-05-20",
      "url": "https://eiga.com/news/20260521/1/"
    },
    {
      "title": "ペドロ・パスカル、マンダロリアン姿でディズニーランドにサプライズ登場",
      "source": "映画.com",
      "date": "2026-05-20",
      "url": "https://eiga.com/news/20260520/26/"
    },
    {
      "title": "アニメ映画「君と花火と約束と」主題歌はtimeleszの新曲、本予告も披露　高橋李依、横澤夏子の出演も決定",
      "source": "映画.com",
      "date": "2026-05-20",
      "url": "https://eiga.com/news/20260520/25/"
    },
    {
      "title": "舘ひろし、西野七瀬にまさかのお願い「冷たく突き放して」【「免許返納!?」プレミアイベント】",
      "source": "映画.com",
      "date": "2026-05-20",
      "url": "https://eiga.com/news/20260520/27/"
    },
    {
      "title": "「おとなになりたくなれますように」村田監督インタビュー　夢の中での親友との再会から生まれた忘れるための映画",
      "source": "映画.com",
      "date": "2026-05-20",
      "url": "https://eiga.com/news/20260520/24/"
    },
    {
      "title": "「黒岩メダカに私の可愛いが通じない」シーズン2、あざとかわいいティザービジュアル＆PV公開",
      "source": "映画.com",
      "date": "2026-05-20",
      "url": "https://eiga.com/news/20260520/23/"
    },
    {
      "title": "ポール・シュレイダー、AIガールフレンドにフラれる",
      "source": "映画.com",
      "date": "2026-05-20",
      "url": "https://eiga.com/news/20260520/22/"
    },
    {
      "title": "「グレイズ・アナトミー」、シリーズ4作目のスピンオフが決定",
      "source": "映画.com",
      "date": "2026-05-20",
      "url": "https://eiga.com/news/20260520/15/"
    },
    {
      "title": "「スター・ウォーズ」劇場公開された実写11作品を振り返り【「マンダロリアン・アンド・グローグー」公開記念】",
      "source": "映画.com",
      "date": "2026-05-20",
      "url": "https://eiga.com/news/20260520/21/"
    },
    {
      "title": "ホセ・ルイス・ゲリン、10年ぶりの新作「よき谷の物語」7月3日公開　「シルビアのいる街で」もリバイバル上映",
      "source": "映画.com",
      "date": "2026-05-20",
      "url": "https://eiga.com/news/20260520/17/"
    },
    {
      "title": "特集「21世紀のジャン＝リュック・ゴダール」予告、生前の坂本龍一氏がゴダール作品に寄せたコメント公開",
      "source": "映画.com",
      "date": "2026-05-20",
      "url": "https://eiga.com/news/20260520/18/"
    },
    {
      "title": "俳優・磯村勇斗、故郷・静岡で映画祭をプロデュースする真意【独占インタビュー】",
      "source": "映画.com",
      "date": "2026-05-20",
      "url": "https://eiga.com/news/20260520/16/"
    },
    {
      "title": "2025年アメリカで最も視聴された番組！「ブルーイ ミニストーリー」シーズン2が5月20日配信決定",
      "source": "映画.com",
      "date": "2026-05-20",
      "url": "https://eiga.com/news/20260520/14/"
    },
    {
      "title": "ハリウッドアニメ版「ハローキティ」の監督が決定",
      "source": "映画.com",
      "date": "2026-05-20",
      "url": "https://eiga.com/news/20260520/12/"
    },
    {
      "title": "「超かぐや姫！」ブルーレイが9月9日発売　特装限定版は予約殺到で在庫切れ、増産に向けた生産体制の強化を検討中",
      "source": "映画.com",
      "date": "2026-05-20",
      "url": "https://eiga.com/news/20260520/13/"
    }
  ],
  "bd_releases": [],
  "retrospectives": [],
  "industry": [],
  "tech": [],
  "festivals": [],
  "international": [],
  "industry_affairs": []
}