{
  "generated_at": "2025-11-19T00:43:59.597628",
  "top_stories": [
    {
      "title": "Children’s & Family Emmy Nominees: Ms. Rachel, June Squibb and a Lisa Kudrow/David Schwimmer ‘Friends’ Face-off",
      "source": "Variety",
      "date": "2025-11-19",
      "url": "https://variety.com/2025/tv/news/childrens-family-emmy-nominees-ms-rachel-june-squibb-1236584194/"
    },
    {
      "title": "‘Dead to Rights’ Review: A Gripping Survival Story Set During the Nanjing Massacre",
      "source": "Variety",
      "date": "2025-11-19",
      "url": "https://variety.com/2025/film/reviews/dead-to-rights-review-china-oscar-entry-1236581714/"
    },
    {
      "title": "Making New York Safer for a Generation: Reisenbach Philanthropies Marks 35 Years of Good Works",
      "source": "Variety",
      "date": "2025-11-18",
      "url": "https://variety.com/2025/biz/news/reisenbach-philanthropies-35-benefit-ny-amy-naomi-ryan-1236585140/"
    }
  ],
  "new_releases": [
    {
      "title": "佐藤二朗原作・脚本・主演サイコバイオレンス「名無し」に丸山隆平、MEGUMI、佐々木蔵之介",
      "source": "映画.com",
      "date": "2025-11-19",
      "url": "https://eiga.com/news/20251119/13/"
    },
    {
      "title": "喜劇王のドキュメント「チャップリン」日本版ビジュアル公開　チャップリンの名作一挙上映の特集開催",
      "source": "映画.com",
      "date": "2025-11-19",
      "url": "https://eiga.com/news/20251119/12/"
    },
    {
      "title": "水上恒司×濱尾ノリタカ、同い年2人の“本気”が伝わる「ウィンドブレイカー」タイマンアクションシーンを披露！",
      "source": "映画.com",
      "date": "2025-11-18",
      "url": "https://eiga.com/news/20251119/9/"
    },
    {
      "title": "山下智久、ほぼスタントなしでフリーダイビングに挑戦　「神の雫 Drops of God」シーズン2、26年1月23日配信【コメント全文】",
      "source": "映画.com",
      "date": "2025-11-18",
      "url": "https://eiga.com/news/20251119/11/"
    },
    {
      "title": "中尾明慶×高橋克実×内田理央が共演、第36回フジテレビヤングシナリオ大賞受賞作「人質は脚本家」映像化！",
      "source": "映画.com",
      "date": "2025-11-18",
      "url": "https://eiga.com/news/20251119/8/"
    },
    {
      "title": "山田涼介、「ズートピア2」イベントにサプライズ登場　念願の“ディズニーファミリー”入りに歓喜",
      "source": "映画.com",
      "date": "2025-11-18",
      "url": "https://eiga.com/news/20251119/5/"
    },
    {
      "title": "東野圭吾原作の劇場アニメ「クスノキの番人」追加声優キャストに齋藤飛鳥、宮世琉弥、大沢たかお　予告映像も公開",
      "source": "映画.com",
      "date": "2025-11-18",
      "url": "https://eiga.com/news/20251119/6/"
    },
    {
      "title": "横浜流星、「イクサガミ」に最狂の剣士役で出演していた！　血飛沫を浴びながら満面の笑みを浮かべる場面カット公開",
      "source": "映画.com",
      "date": "2025-11-18",
      "url": "https://eiga.com/news/20251119/7/"
    },
    {
      "title": "卒業生たちが再結集！　木村拓哉主演「教場 Reunion」本ビジュアル、予告、追加キャスト発表",
      "source": "映画.com",
      "date": "2025-11-18",
      "url": "https://eiga.com/news/20251119/3/"
    },
    {
      "title": "舞台「ハリー・ポッターと呪いの子」2026年12月27日に千秋楽　4年半のロングラン公演に幕",
      "source": "映画.com",
      "date": "2025-11-18",
      "url": "https://eiga.com/news/20251119/2/"
    },
    {
      "title": "東映太秦映画村、大人の没入体験パークへフルリニューアル！　コンセプトは「江戸時代の京へ、迷い込む」、26年3月28日第1期オープン",
      "source": "映画.com",
      "date": "2025-11-18",
      "url": "https://eiga.com/news/20251119/1/"
    },
    {
      "title": "メリル・ストリープ＆シガニー・ウィーバーが新作「Useful Idiots」で共演",
      "source": "映画.com",
      "date": "2025-11-18",
      "url": "https://eiga.com/news/20251118/33/"
    },
    {
      "title": "TRIGGER×雨宮哲の青春ショートアニメシリーズ「ザ・レンチキュラーズ」が配信中",
      "source": "映画.com",
      "date": "2025-11-18",
      "url": "https://eiga.com/news/20251118/32/"
    },
    {
      "title": "マイケル・マン監督「ヒート」続編にクリスチャン・ベールが主演か",
      "source": "映画.com",
      "date": "2025-11-18",
      "url": "https://eiga.com/news/20251118/31/"
    },
    {
      "title": "実写版「ゼルダの伝説」リンク＆ゼルダのビジュアル初公開",
      "source": "映画.com",
      "date": "2025-11-18",
      "url": "https://eiga.com/news/20251118/29/"
    },
    {
      "title": "「バーチャルさんはみている」全12話が無料配信中　ミライアカリ、電脳少女シロらVTuberが多数出演",
      "source": "映画.com",
      "date": "2025-11-18",
      "url": "https://eiga.com/news/20251118/28/"
    },
    {
      "title": "板垣李光人、大学生に「毎日を大切に思えるきっかけになってほしい」と訴え【「ペリリュー　楽園のゲルニカ」試写会】",
      "source": "映画.com",
      "date": "2025-11-18",
      "url": "https://eiga.com/news/20251118/26/"
    },
    {
      "title": "【大ヒット中】「爆弾」重要スポットのロケ地ガイド　物語の中心となる野方警察署、巡査バディが訪れる喫茶店",
      "source": "映画.com",
      "date": "2025-11-18",
      "url": "https://eiga.com/news/20251118/21/"
    },
    {
      "title": "「SEVENTEEN」ジュンが老人に変身！　「シャドウズ・エッジ」本編映像公開",
      "source": "映画.com",
      "date": "2025-11-18",
      "url": "https://eiga.com/news/20251118/20/"
    },
    {
      "title": "大物俳優、自分探しの旅へ　ジョージ・クルーニー×ノア・バームバック監督「ジェイ・ケリー」キービジュアル＆本予告",
      "source": "映画.com",
      "date": "2025-11-18",
      "url": "https://eiga.com/news/20251118/23/"
    },
    {
      "title": "橋本梨菜、“令和のキューティハニー” に挑む最恐ヴィランに決定　過激コスチュームで迫力バトルも",
      "source": "映画.com",
      "date": "2025-11-18",
      "url": "https://eiga.com/news/20251118/22/"
    },
    {
      "title": "「ペリリュー　楽園のゲルニカ」の舞台を板垣李光⼈が訪問した特別番組放送決定",
      "source": "映画.com",
      "date": "2025-11-18",
      "url": "https://eiga.com/news/20251118/25/"
    },
    {
      "title": "「バーフバリ　エピック4K」の“バーフバリ王”プラバース緊急来日決定",
      "source": "映画.com",
      "date": "2025-11-18",
      "url": "https://eiga.com/news/20251118/24/"
    },
    {
      "title": "武装強盗団が電車で襲撃開始→最強の特殊部隊員も乗っていた…　「KILL 超覚醒」重要シーン公開",
      "source": "映画.com",
      "date": "2025-11-18",
      "url": "https://eiga.com/news/20251118/19/"
    },
    {
      "title": "「小3アシベ QQ ゴマちゃん」ショートアニメ化決定　「鷹の爪」のDLE制作で26年放送",
      "source": "映画.com",
      "date": "2025-11-18",
      "url": "https://eiga.com/news/20251118/18/"
    },
    {
      "title": "目黒蓮、「SHOGUN 将軍」シーズン2に出演決定「本当に夢のよう」　新キャラクター・和忠役",
      "source": "映画.com",
      "date": "2025-11-18",
      "url": "https://eiga.com/news/20251118/30/"
    }
  ],
  "bd_releases": [],
  "retrospectives": [],
  "industry": [],
  "tech": [],
  "festivals": [],
  "international": [],
  "industry_affairs": []
}