{
  "generated_at": "2026-06-04T09:37:50.154236",
  "top_stories": [
    {
      "title": "M-Appeal Seals Cannes Deals on ‘Downtown,’ ‘The Garden We Dreamed,’ ‘Truly Naked’ (EXCLUSIVE)",
      "source": "Variety",
      "date": "2026-06-04",
      "url": "https://variety.com/2026/film/global/m-appeal-cannes-downtown-the-garden-we-dreamed-truly-naked-1236766268/"
    },
    {
      "title": "Channing Tatum, Gemma Chan Sundance Winner ‘Josephine’ Lands Indian Subcontinent Rights With Fragrant Nature Film Creations (EXCLUSIVE)",
      "source": "Variety",
      "date": "2026-06-04",
      "url": "https://variety.com/2026/film/news/channing-tatum-gemma-chan-sundance-josephine-india-rights-1236766418/"
    },
    {
      "title": "Tribeca Kicks Off With Earth, Wind & Fire Documentary and Robert De Niro Dissing Trump as ‘Immoral, Cruel and Corrupt’",
      "source": "Variety",
      "date": "2026-06-04",
      "url": "https://variety.com/2026/film/news/tribeca-opening-night-robert-de-niro-slams-trump-1236766383/"
    }
  ],
  "new_releases": [
    {
      "title": "タランティーノ、近年のハリウッドは「味のないソーセージ工場」",
      "source": "映画.com",
      "date": "2026-06-04",
      "url": "https://eiga.com/news/20260604/18/"
    },
    {
      "title": "板垣李光人主演「口に関するアンケート」大ヒット小説映像化のプロセスを清水崇監督が解説、キャストの新たな証言画像公開",
      "source": "映画.com",
      "date": "2026-06-04",
      "url": "https://eiga.com/news/20260604/16/"
    },
    {
      "title": "トラビス・ナイト監督が⽇本⽂化からの影響を熱弁！「マスターズ・オブ・ユニバース」特別映像公開",
      "source": "映画.com",
      "date": "2026-06-04",
      "url": "https://eiga.com/news/20260604/15/"
    },
    {
      "title": "漫画家・真崎守の妻が41歳差婚の生活をつづったコミックエッセイが発売中",
      "source": "映画.com",
      "date": "2026-06-04",
      "url": "https://eiga.com/news/20260604/14/"
    },
    {
      "title": "「怪獣8号」ショートアニメ「鳴海の平日」今秋に配信決定　メインビジュアル公開",
      "source": "映画.com",
      "date": "2026-06-04",
      "url": "https://eiga.com/news/20260604/13/"
    },
    {
      "title": "28年前期朝ドラは「ほんのモキチ」　主演・河合優実×作・宮藤官九郎の「ふてほど」コンビ",
      "source": "映画.com",
      "date": "2026-06-04",
      "url": "https://eiga.com/news/20260604/17/"
    },
    {
      "title": "ブラッド・ピット「フレンズ」収録では緊張しきり？ 元妻アニストンが述懐",
      "source": "映画.com",
      "date": "2026-06-04",
      "url": "https://eiga.com/news/20260604/12/"
    },
    {
      "title": "「トランスフォーマー」のシャイア・ラブーフ、暴行罪を認め保護観察に",
      "source": "映画.com",
      "date": "2026-06-04",
      "url": "https://eiga.com/news/20260604/10/"
    },
    {
      "title": "有村架純主演「マジカル・シークレット・ツアー」、黒木華と青木柚の熱狂的な“推し活”を捉えた本編映像",
      "source": "映画.com",
      "date": "2026-06-04",
      "url": "https://eiga.com/news/20260604/9/"
    },
    {
      "title": "小さな歌姫が恐怖へ誘う！　「だぁれかさんとアソぼ？」エンディングテーマ担当にののちゃんが決定＆楽曲入りの新予告映像を披露",
      "source": "映画.com",
      "date": "2026-06-04",
      "url": "https://eiga.com/news/20260604/8/"
    },
    {
      "title": "ジョディ・フォスターが脚本を読んで出演を即決したフランス映画「プライベート・ケース」流暢なフランス語を披露する予告映像公開",
      "source": "映画.com",
      "date": "2026-06-04",
      "url": "https://eiga.com/news/20260604/6/"
    },
    {
      "title": "「映画大好きポンポさん」制作チーム最新作「WASTED CHEF」特報を公開　コミカライズ連載も決定",
      "source": "映画.com",
      "date": "2026-06-04",
      "url": "https://eiga.com/news/20260604/7/"
    },
    {
      "title": "DCユニバース最新作「スーパーガール」、初出しアクション満載の特別映像＆キャラクターポスターを披露",
      "source": "映画.com",
      "date": "2026-06-04",
      "url": "https://eiga.com/news/20260604/5/"
    },
    {
      "title": "全員「パスト ライブス　再会」の大ファンだった！ダコタ・ジョンソン＆クリス・エバンス＆ペドロ・パスカル相思相愛の出演秘話",
      "source": "映画.com",
      "date": "2026-06-04",
      "url": "https://eiga.com/news/20260604/4/"
    },
    {
      "title": "「アベンジャーズ　ドゥームズデイ」でMCUはフェーズ・ゼロへ戻る　ルッソ兄弟が語る",
      "source": "映画.com",
      "date": "2026-06-03",
      "url": "https://eiga.com/news/20260604/3/"
    },
    {
      "title": "“まさか”の連続！「私がビーバーになる時」6月10日からディズニープラスで見放題独占配信",
      "source": "映画.com",
      "date": "2026-06-03",
      "url": "https://eiga.com/news/20260604/2/"
    },
    {
      "title": "「世にも奇妙な物語 ’26夏の特別編」6月27日放送！上川隆也がベテラン刑事役で奇妙な世界へ",
      "source": "映画.com",
      "date": "2026-06-03",
      "url": "https://eiga.com/news/20260604/1/"
    },
    {
      "title": "「天体戦士サンレッド」初の舞台化　髙木俊らアニメキャストを起用した“実写版”ヒーローショーとしてシアターGロッソで上演",
      "source": "映画.com",
      "date": "2026-06-03",
      "url": "https://eiga.com/news/20260603/20/"
    },
    {
      "title": "「美女と野獣」「アラジン」楽曲を歌ったピーボ・ブライソンさん死去　75歳",
      "source": "映画.com",
      "date": "2026-06-03",
      "url": "https://eiga.com/news/20260603/26/"
    },
    {
      "title": "大ヒットホラー「バックルームズ」の続編企画が始動",
      "source": "映画.com",
      "date": "2026-06-03",
      "url": "https://eiga.com/news/20260603/23/"
    },
    {
      "title": "生誕120年ジョン・ヒューストン特集開催「アフリカの女王」4Kなど4作品上映",
      "source": "映画.com",
      "date": "2026-06-03",
      "url": "https://eiga.com/news/20260603/18/"
    },
    {
      "title": "“奇跡のバンド”をオール福井ロケで映画化「きみの音が見えたとき」27年秋公開　田辺桃子＆仲村トオルが親子役",
      "source": "映画.com",
      "date": "2026-06-03",
      "url": "https://eiga.com/news/20260603/19/"
    },
    {
      "title": "少女時代・ユナとアン・ボヒョンが日本のファンにメッセージ！　「プリティ・クレイジー　悪魔が引っ越してきた」特別映像＆キャラポスも披露",
      "source": "映画.com",
      "date": "2026-06-03",
      "url": "https://eiga.com/news/20260603/16/"
    },
    {
      "title": "ザック・スナイダー、ジョン・カーペンター監督作「ニューヨーク1997」をリメイクへ",
      "source": "映画.com",
      "date": "2026-06-03",
      "url": "https://eiga.com/news/20260603/17/"
    },
    {
      "title": "「魔法のプリンセス ミンキーモモ」新作OVA、11月13日に劇場公開　前シリーズの総監督・湯山邦彦氏からコメント到着",
      "source": "映画.com",
      "date": "2026-06-03",
      "url": "https://eiga.com/news/20260603/14/"
    },
    {
      "title": "ダニー・ボイル監督、「28年後...」3部作の完結編は「うまくいけば来年には撮影ができる」",
      "source": "映画.com",
      "date": "2026-06-03",
      "url": "https://eiga.com/news/20260603/13/"
    },
    {
      "title": "「ドロヘドロ Season3」製作決定　林祐一郎監督のイラスト、2期・OPテーマのアニメMVが公開",
      "source": "映画.com",
      "date": "2026-06-03",
      "url": "https://eiga.com/news/20260603/12/"
    },
    {
      "title": "生誕100年のマリリン・モンロー、そっくりさん1000人超が世界記録",
      "source": "映画.com",
      "date": "2026-06-03",
      "url": "https://eiga.com/news/20260603/11/"
    }
  ],
  "bd_releases": [],
  "retrospectives": [],
  "industry": [],
  "tech": [],
  "festivals": [],
  "international": [],
  "industry_affairs": []
}