{
  "generated_at": "2026-02-18T01:02:49.799286",
  "top_stories": [
    {
      "title": "Warner Bros. Blasts ByteDance for AI Videos of Superman, Batman and ‘Game of Thrones’",
      "source": "Variety",
      "date": "2026-02-18",
      "url": "https://variety.com/2026/film/news/warner-bros-bytedance-ai-batman-superman-game-of-thrones-1236665979/"
    },
    {
      "title": "‘Who Killed Alex Odeh?’ Review: A Modest True Crime Doc Where the Answers Are Out in the Open",
      "source": "Variety",
      "date": "2026-02-17",
      "url": "https://variety.com/2026/film/reviews/who-killed-alex-odeh-review-1236664721/"
    },
    {
      "title": "Daniel Radcliffe Tells Press Not to Always Ask HBO’s ‘Harry Potter’ Cast About the Original Movie Actors: ‘Just Let Them Get On… It’s Going to Be Different’",
      "source": "Variety",
      "date": "2026-02-17",
      "url": "https://variety.com/2026/tv/news/daniel-radcliffe-harry-potter-new-cast-original-movies-1236665918/"
    }
  ],
  "new_releases": [
    {
      "title": "日本の動画配信市場が1兆1000億円を突破、Netflix・Amazon・U-NEXTが三つ巴",
      "source": "映画.com",
      "date": "2026-02-18",
      "url": "https://eiga.com/news/20260218/9/"
    },
    {
      "title": "山田杏奈×ショーン・ティア主演「ロスト・アンド・ファウンド　君を探して」共演に村上虹郎、森田想、大東駿介、杉本哲太ら集結",
      "source": "映画.com",
      "date": "2026-02-18",
      "url": "https://eiga.com/news/20260218/8/"
    },
    {
      "title": "柄本佑主演「メモリィズ」穂志もえか、香椎由宇、イッセー尾形ら新キャスト発表",
      "source": "映画.com",
      "date": "2026-02-17",
      "url": "https://eiga.com/news/20260218/7/"
    },
    {
      "title": "土屋太鳳「ずっと憧れだった」アンパンマンファミリーの仲間入り！　映画最新作でゲスト声優に",
      "source": "映画.com",
      "date": "2026-02-17",
      "url": "https://eiga.com/news/20260218/6/"
    },
    {
      "title": "松本潤、山田裕貴主演「ちるらん　新撰組鎮魂歌」に出演　“幕末のカリスマ”松平容保役「また一緒に芝居ができるのが楽しみでした」",
      "source": "映画.com",
      "date": "2026-02-17",
      "url": "https://eiga.com/news/20260218/5/"
    },
    {
      "title": "玉木宏「プロフェッショナル　保険調査員・天音蓮」に堀田茜、SixTONES髙地優吾、平野美宇らがゲスト出演！",
      "source": "映画.com",
      "date": "2026-02-17",
      "url": "https://eiga.com/news/20260218/3/"
    },
    {
      "title": "ダニエル・ラドクリフ、新「ハリー・ポッター」キャストへの思いを語る",
      "source": "映画.com",
      "date": "2026-02-17",
      "url": "https://eiga.com/news/20260217/26/"
    },
    {
      "title": "織田裕二が再び社会の巨悪を暴く「アンダークラス」制作決定【「ガラパゴス」続編】",
      "source": "映画.com",
      "date": "2026-02-17",
      "url": "https://eiga.com/news/20260217/25/"
    },
    {
      "title": "ハル・ハートリー監督11年ぶりの最新作「トゥ・ランド」公開決定 コロナ禍による製作中止を乗り越えついに完成",
      "source": "映画.com",
      "date": "2026-02-17",
      "url": "https://eiga.com/news/20260217/27/"
    },
    {
      "title": "ジェジュンが廃神社での撮影に挑む「神社　悪魔のささやき」メイキング写真公開　新たな入場者特典も発表",
      "source": "映画.com",
      "date": "2026-02-17",
      "url": "https://eiga.com/news/20260217/24/"
    },
    {
      "title": "「映画　えんとつ町のプペル　約束の時計台」ベルリン国際映画祭で初お披露目　西野亮廣、着想の原点を語る「待つということはすごく勇気のいる判断」",
      "source": "映画.com",
      "date": "2026-02-17",
      "url": "https://eiga.com/news/20260217/23/"
    },
    {
      "title": "日本劇場初公開作含む絶望的傑作4本「チェコ映画傑作選」4月10日公開",
      "source": "映画.com",
      "date": "2026-02-17",
      "url": "https://eiga.com/news/20260217/21/"
    },
    {
      "title": "「ゴッドファーザー」「地獄の黙示録」のロバート・デュバルさん死去、95歳",
      "source": "映画.com",
      "date": "2026-02-17",
      "url": "https://eiga.com/news/20260217/35/"
    },
    {
      "title": "アクション・スタント界のレジェンドが大集結！「クライム101」クリス・ヘムズワースの運転テクニック特別映像公開",
      "source": "映画.com",
      "date": "2026-02-17",
      "url": "https://eiga.com/news/20260217/20/"
    },
    {
      "title": "2025年の中国映画市場を徹底分析！　観客と映画館の関係に変化、「ナタ　魔童の大暴れ」の存在感、日本映画の行方は？【アジア映画コラム】",
      "source": "映画.com",
      "date": "2026-02-17",
      "url": "https://eiga.com/news/20260217/18/"
    },
    {
      "title": "日本のアニメはアメリカを「制した」のか？　北米興行の数字が語ること【ハリウッドコラムvol.371】",
      "source": "映画.com",
      "date": "2026-02-17",
      "url": "https://eiga.com/news/20260217/17/"
    },
    {
      "title": "漫画「涙雨とセレナーデ」27年TVアニメ化　女子高生と御曹司のタイムスリップ・ロマンス",
      "source": "映画.com",
      "date": "2026-02-17",
      "url": "https://eiga.com/news/20260217/14/"
    },
    {
      "title": "インドに刻まれた、建築の巨匠の対話　特集「ル・コルビュジエとドーシ インドのモダニズム」5月1日から",
      "source": "映画.com",
      "date": "2026-02-17",
      "url": "https://eiga.com/news/20260217/15/"
    },
    {
      "title": "意味深セリフで新たな展開を予感！チェ・ジョンヒョプ主演「君がきらめく季節に」新たなティザー予告編＆ポスター公開",
      "source": "映画.com",
      "date": "2026-02-17",
      "url": "https://eiga.com/news/20260217/13/"
    },
    {
      "title": "女子高生が雑草を研究？「ザッケン！」4月3日公開　ポスター＆予告披露",
      "source": "映画.com",
      "date": "2026-02-17",
      "url": "https://eiga.com/news/20260217/9/"
    },
    {
      "title": "「AKIRA」などアニメ映画で幕開ける「午前十時の映画祭16」、20本新規の全25本ラインナップ決定！",
      "source": "映画.com",
      "date": "2026-02-17",
      "url": "https://eiga.com/news/20260217/10/"
    },
    {
      "title": "「天国の味わいだ！」ブレンダン・フレイザー＆柄本明がお好み焼きを囲んで心を通わせる「レンタル・ファミリー」本編映像",
      "source": "映画.com",
      "date": "2026-02-17",
      "url": "https://eiga.com/news/20260217/11/"
    },
    {
      "title": "佐久間大介主演「スペシャルズ」銃撃アクションクリップ映像披露　伝説の元殺し屋“ダイヤ”の登場にも注目",
      "source": "映画.com",
      "date": "2026-02-17",
      "url": "https://eiga.com/news/20260217/12/"
    },
    {
      "title": "「KPOPガールズ！」「ハリー・ポッター」効果で米玩具大手株が上昇",
      "source": "映画.com",
      "date": "2026-02-17",
      "url": "https://eiga.com/news/20260217/8/"
    },
    {
      "title": "「スノウボールアース」オープニング主題歌「零-zero-」を現役女子高生シンガーtuki.が歌唱",
      "source": "映画.com",
      "date": "2026-02-17",
      "url": "https://eiga.com/news/20260217/7/"
    }
  ],
  "bd_releases": [],
  "retrospectives": [],
  "industry": [],
  "tech": [],
  "festivals": [],
  "international": [],
  "industry_affairs": []
}