{
  "generated_at": "2026-07-05T05:50:47.044157",
  "top_stories": [
    {
      "title": "‘The Pitt’ Star Noah Wyle Was Offered Roles in ‘Saving Private Ryan’ and ‘Good Night, and Good Luck’ but ‘Couldn’t Get Out’ of Filming ‘ER’",
      "source": "Variety",
      "date": "2026-07-04",
      "url": "https://variety.com/2026/film/news/the-pitt-noah-wyle-saving-private-ryan-er-1236801812/"
    },
    {
      "title": "Vin Diesel Shares Behind-the-Scenes Look at ‘Fast Forever’: ‘We’ve Been Grinding’",
      "source": "Variety",
      "date": "2026-07-04",
      "url": "https://variety.com/2026/film/news/vin-diesel-behind-the-scenes-fast-forever-1236801804/"
    },
    {
      "title": "Abdullah Mason vs. Albert Bell Boxing Livestream: How to Watch TNT Sports’ ‘The Fight’ Online for Free",
      "source": "Variety",
      "date": "2026-07-04",
      "url": "https://variety.com/2026/shopping/news/abdullah-mason-albert-bell-boxing-fight-free-stream-online-1236801043/"
    }
  ],
  "new_releases": [
    {
      "title": "ポール・ダノ　リメイク版「ポゼッション」に出演",
      "source": "映画.com",
      "date": "2026-07-05",
      "url": "https://eiga.com/news/20260705/8/"
    },
    {
      "title": "映画「オデュッセイア」を「地球の歩き方」がガチ案内！コラボWEB特集スタート＆原案コミカライズも決定",
      "source": "映画.com",
      "date": "2026-07-05",
      "url": "https://eiga.com/news/20260705/7/"
    },
    {
      "title": "ドラムの壮絶で希望に満ちた“過去”が明らかに！「VIVANT」サイドストーリー、U-NEXT独占配信　大谷亮平＆渡辺銀次が出演",
      "source": "映画.com",
      "date": "2026-07-05",
      "url": "https://eiga.com/news/20260705/6/"
    },
    {
      "title": "唐沢寿明×広瀬アリス“時が流れても変わらない”「トイ・ストーリー」の魅力とは？【「トイ・ストーリー5」インタビュー】",
      "source": "映画.com",
      "date": "2026-07-05",
      "url": "https://eiga.com/news/20260705/5/"
    },
    {
      "title": "新仮面ライダーはネズミ!? 「仮面ライダーマイス」9月放送スタート ネコのライダーも登場",
      "source": "映画.com",
      "date": "2026-07-05",
      "url": "https://eiga.com/news/20260705/4/"
    },
    {
      "title": "「杖と剣のウィストリア」シーズン3が製作決定　サウンドトラックが配信リリース開始",
      "source": "映画.com",
      "date": "2026-07-05",
      "url": "https://eiga.com/news/20260705/3/"
    },
    {
      "title": "「ガチャを回して仲間を増やす　最強の美少女軍団を作り上げろ」TVアニメ化、27年1月放送開始　メインキャストに阪口大助、富田美憂、「＝LOVE」野口衣織",
      "source": "映画.com",
      "date": "2026-07-04",
      "url": "https://eiga.com/news/20260705/2/"
    },
    {
      "title": "米映画館チェーン、行き場を失った映画祭作品の劇場公開に乗り出す",
      "source": "映画.com",
      "date": "2026-07-04",
      "url": "https://eiga.com/news/20260704/15/"
    },
    {
      "title": "「鍋に弾丸を受けながら」J.C.STAFF制作で27年TVアニメ化　美少女（中身はおじさん）の海外グルメ旅",
      "source": "映画.com",
      "date": "2026-07-04",
      "url": "https://eiga.com/news/20260704/14/"
    },
    {
      "title": "提訴された画像生成AIのMidjourney、大手に「社内でのAI利用有無を明かせ」と要求",
      "source": "映画.com",
      "date": "2026-07-04",
      "url": "https://eiga.com/news/20260704/13/"
    },
    {
      "title": "「攻殻機動隊」新作TVアニメは“ミリしら”の人にこそお勧め　「原作コミックへの原点回帰」を読み解く",
      "source": "映画.com",
      "date": "2026-07-04",
      "url": "https://eiga.com/news/20260704/12/"
    },
    {
      "title": "中島健人主演「ラブ≠コメディ」にWEST.重岡大毅が友情出演！場面写真＆仲良しオフショット披露",
      "source": "映画.com",
      "date": "2026-07-04",
      "url": "https://eiga.com/news/20260704/11/"
    },
    {
      "title": "「今までと少し違った雰囲気になっているかも」ピーター・パーカー役・榎木淳弥、ハルク役吹替の宮内敦士とともに「スパイダーマン」新章に続投",
      "source": "映画.com",
      "date": "2026-07-04",
      "url": "https://eiga.com/news/20260704/10/"
    },
    {
      "title": "「マリッジトキシン」第2期、27年1月から放送決定　原作者からお祝いのコメント",
      "source": "映画.com",
      "date": "2026-07-04",
      "url": "https://eiga.com/news/20260704/9/"
    },
    {
      "title": "北川景子主演「ナイトフラワー」を日本映画専門チャンネルでテレビ初放送！　「夜に咲く、愛と欲望の映画たち」特集なども",
      "source": "映画.com",
      "date": "2026-07-04",
      "url": "https://eiga.com/news/20260704/8/"
    },
    {
      "title": "建築ファンタジー漫画「ソアラと魔物の家」27年にTVアニメ化　長谷川育美、村瀬歩が出演　PV＆ビジュアル公開",
      "source": "映画.com",
      "date": "2026-07-04",
      "url": "https://eiga.com/news/20260704/7/"
    },
    {
      "title": "Netflixシリーズ「ガス人間」作品概要、あらすじ、キャラクター、スタッフ、予告編まとめ",
      "source": "映画.com",
      "date": "2026-07-04",
      "url": "https://eiga.com/news/20260704/6/"
    },
    {
      "title": "デル・トロ監督ら3人、アカデミー映画博物館の理事に就任",
      "source": "映画.com",
      "date": "2026-07-04",
      "url": "https://eiga.com/news/20260704/5/"
    },
    {
      "title": "【ディズニープラス　7月配信作】「アバター」最新作、「X-Men '97」「攻殻機動隊」など強力SFタイトルが続々！ファン待望の「殺し屋たちの店 2」も",
      "source": "映画.com",
      "date": "2026-07-04",
      "url": "https://eiga.com/news/20260704/4/"
    },
    {
      "title": "「すだちの魔王城」project No.9制作で27年1月放送開始　川島零士、大久保瑠美が出演　ティザーPVでボイス初公開",
      "source": "映画.com",
      "date": "2026-07-04",
      "url": "https://eiga.com/news/20260704/3/"
    },
    {
      "title": "「THE RIBBON HERO」第2弾予告を披露　主題歌は日韓新ユニット、追加キャストに小林星蘭、内山昂輝、新谷真弓",
      "source": "映画.com",
      "date": "2026-07-03",
      "url": "https://eiga.com/news/20260704/2/"
    },
    {
      "title": "スパイダーマンをニューヨークに呼び戻せ　市が大作ロケの誘致に本腰",
      "source": "映画.com",
      "date": "2026-07-03",
      "url": "https://eiga.com/news/20260703/31/"
    },
    {
      "title": "「ワールド イズ ダンシング」第1話放送を記念して、井上雄彦のお祝いイラスト公開　OP映像も披露",
      "source": "映画.com",
      "date": "2026-07-03",
      "url": "https://eiga.com/news/20260703/30/"
    },
    {
      "title": "「ユーリ!!! on ICE」7月17日からYouTubeで全話一挙配信　10周年を記念してキャストらが喜びのコメント",
      "source": "映画.com",
      "date": "2026-07-03",
      "url": "https://eiga.com/news/20260703/29/"
    },
    {
      "title": "M!LKの塩﨑太智と吉田仁人が「トイ・ストーリー5」にカメオ声優出演！　塩崎「踊りたくなっち ゃうくらい最高」　吉田「幸せでした」",
      "source": "映画.com",
      "date": "2026-07-03",
      "url": "https://eiga.com/news/20260703/28/"
    },
    {
      "title": "「ダイヤのA actII -Second Season-」第2クールは10月放送開始　GLAYがOP主題歌、OxTがED主題歌で決勝戦に華を添える",
      "source": "映画.com",
      "date": "2026-07-03",
      "url": "https://eiga.com/news/20260703/26/"
    },
    {
      "title": "アニメ「モアナと伝説の海」3作目が進行中　マウイ役のドウェイン・ジョンソン明かす",
      "source": "映画.com",
      "date": "2026-07-03",
      "url": "https://eiga.com/news/20260703/27/"
    },
    {
      "title": "市川雷蔵主演「眠狂四郎」シリーズ全12作を「BS10プレミアム」で一挙放送！ 孤高の色気と虚無感を漂わせる“番宣映像”公開",
      "source": "映画.com",
      "date": "2026-07-03",
      "url": "https://eiga.com/news/20260703/23/"
    }
  ],
  "bd_releases": [],
  "retrospectives": [],
  "industry": [],
  "tech": [],
  "festivals": [],
  "international": [],
  "industry_affairs": []
}